mopeka_ble/__init__.py
mopeka_ble/parser.py
mopeka_ble/py.typed
mopeka_ble-0.2.5.dist-info/LICENSE
mopeka_ble-0.2.5.dist-info/METADATA
mopeka_ble-0.2.5.dist-info/WHEEL
mopeka_ble-0.2.5.dist-info/RECORD
