Metadata-Version: 2.1
Name: mopeka-ble
Version: 0.2.5
Summary: Parser for Mopeka bluetooth tank sensors
Home-page: https://github.com/lekobob/mopeka-ble
License: MIT
Author: Joshua Hahn
Author-email: josh.w.hahn@gmail.com
Requires-Python: >=3.9,<4.0
Classifier: Development Status :: 2 - Pre-Alpha
Classifier: Intended Audience :: Developers
Classifier: License :: OSI Approved :: MIT License
Classifier: Natural Language :: English
Classifier: Operating System :: OS Independent
Classifier: Programming Language :: Python :: 3
Classifier: Programming Language :: Python :: 3.9
Classifier: Programming Language :: Python :: 3.10
Classifier: Programming Language :: Python :: 3.11
Classifier: Topic :: Software Development :: Libraries
Provides-Extra: docs
Requires-Dist: Sphinx (>=5.0,<6.0) ; extra == "docs"
Requires-Dist: bluetooth-data-tools (>=0.1.2)
Requires-Dist: bluetooth-sensor-state-data (>=1.6.0)
Requires-Dist: myst-parser (>=0.19,<0.20) ; extra == "docs"
Requires-Dist: sensor-state-data (>=2.3.2)
Requires-Dist: sphinx-rtd-theme (>=1.0,<2.0) ; extra == "docs"
Project-URL: Bug Tracker, https://github.com/lekobob/mopeka-ble/issues
Project-URL: Changelog, https://github.com/lekobob/mopeka-ble/blob/main/CHANGELOG.md
Project-URL: Documentation, https://mopeka-ble.readthedocs.io
Project-URL: Repository, https://github.com/lekobob/mopeka-ble
